tracepy/__init__.py
tracepy/constants.py
tracepy/exceptions.py
tracepy/geometry.py
tracepy/geoplot.py
tracepy/index.py
tracepy/iotables.py
tracepy/optimize.py
tracepy/optplot.py
tracepy/ray.py
tracepy/raygroup.py
tracepy/transforms.py
tracepy/utils.py
tracepy/glass/glass_dict.json
tracepy/glass/ami/AMTIR-1.yml
tracepy/glass/ami/AMTIR-2.yml
tracepy/glass/ami/AMTIR-3.yml
tracepy/glass/ami/AMTIR-6.yml
tracepy/glass/barberini/D0082.yml
tracepy/glass/barberini/D0191.yml
tracepy/glass/barberini/D0290.yml
tracepy/glass/barberini/D0391.yml
tracepy/glass/barberini/D0587.yml
tracepy/glass/barberini/D0687.yml
tracepy/glass/barberini/D0785.yml
tracepy/glass/barberini/D0888.yml
tracepy/glass/barberini/D0891.yml
tracepy/glass/barberini/D0991.yml
tracepy/glass/barberini/D1125.yml
tracepy/glass/barberini/D1214.yml
tracepy/glass/barberini/D1219.yml
tracepy/glass/barberini/D1230.yml
tracepy/glass/barberini/D1420_1.yml
tracepy/glass/barberini/D1426-D1526.yml
tracepy/glass/barberini/D1511.yml
tracepy/glass/barberini/D1520.yml
tracepy/glass/barberini/D1616.yml
tracepy/glass/barberini/D4150.yml
tracepy/glass/barberini/D5336_1.yml
tracepy/glass/barberini/D6117.yml
tracepy/glass/barberini/D6420.yml
tracepy/glass/barberini/D6526-D6626.yml
tracepy/glass/barberini/D6625.yml
tracepy/glass/barberini/D6726-D6826.yml
tracepy/glass/barberini/D9148.yml
tracepy/glass/cdgm/BAF2.yml
tracepy/glass/cdgm/BAF4.yml
tracepy/glass/cdgm/BAF5.yml
tracepy/glass/cdgm/BAF7.yml
tracepy/glass/cdgm/D-FK61.yml
tracepy/glass/cdgm/D-K59.yml
tracepy/glass/cdgm/D-K9.yml
tracepy/glass/cdgm/D-LAF050.yml
tracepy/glass/cdgm/D-LAF50.yml
tracepy/glass/cdgm/D-LAF53.yml
tracepy/glass/cdgm/D-LAF79.yml
tracepy/glass/cdgm/D-LAF82L.yml
tracepy/glass/cdgm/D-LAK5.yml
tracepy/glass/cdgm/D-LAK6.yml
tracepy/glass/cdgm/D-LAK70.yml
tracepy/glass/cdgm/D-PK3.yml
tracepy/glass/cdgm/D-ZF10.yml
tracepy/glass/cdgm/D-ZF93.yml
tracepy/glass/cdgm/D-ZK2.yml
tracepy/glass/cdgm/D-ZK3.yml
tracepy/glass/cdgm/D-ZK79.yml
tracepy/glass/cdgm/D-ZLAF50.yml
tracepy-0.2.1.dist-info/LICENSE
tracepy-0.2.1.dist-info/METADATA
tracepy-0.2.1.dist-info/WHEEL
tracepy-0.2.1.dist-info/top_level.txt
tracepy-0.2.1.dist-info/RECORD
