Metadata-Version: 2.2
Name: tracepy
Version: 0.2.1
Summary: Optical design software for python.
Home-page: http://github.com/GNiendorf/tracepy
Author: Gavin Niendorf
Author-email: gavinniendorf@gmail.com
License: MIT
Keywords: optics,ray-tracing,optimization,geometrical optics,optical-design,optical-engineering
Platform: any
Classifier: Intended Audience :: Science/Research
Classifier: License :: OSI Approved :: MIT License
Classifier: Programming Language :: Python :: 3.10
Classifier: Programming Language :: Python :: 3.11
Classifier: Programming Language :: Python :: 3.12
License-File: LICENSE
Requires-Dist: numpy
Requires-Dist: matplotlib
Requires-Dist: pandas
Requires-Dist: scipy
Requires-Dist: scikit-learn
Requires-Dist: PyYAML
Dynamic: author
Dynamic: author-email
Dynamic: description
Dynamic: description-content-type
Dynamic: home-page
Dynamic: license
Dynamic: requires-dist
Dynamic: summary
